plattli/__init__.py
plattli/_indices.py
plattli/_version.py
plattli/bulk_writer.py
plattli/jsonl2plattli.py
plattli/reader.py
plattli/writer.py
plattli-0.6.4.dist-info/entry_points.txt
plattli-0.6.4.dist-info/licenses/LICENSE
plattli-0.6.4.dist-info/WHEEL
plattli-0.6.4.dist-info/METADATA
plattli-0.6.4.dist-info/RECORD
