Metadata-Version: 2.4
Name: plattli
Version: 0.6.4
Summary: Plättli is an opinionated dataformat for logging a series of metrics
Keywords: metrics,logging,writer,streaming
Author-email: Lucas Beyer <lucasb.eyer.be@gmail.com>
Requires-Python: >=3.11
Classifier: License :: OSI Approved :: MIT License
Classifier: Programming Language :: Python :: 3
Classifier: Programming Language :: Python :: 3 :: Only
Classifier: Programming Language :: Python :: 3.11
Classifier: Programming Language :: Python :: 3.12
Classifier: Programming Language :: Python :: 3.13
Classifier: Programming Language :: Python :: 3.14
Classifier: Intended Audience :: Developers
Classifier: Operating System :: OS Independent
Classifier: Topic :: Software Development :: Libraries
License-File: LICENSE
Requires-Dist: numpy>=1.20
Project-URL: Changelog, https://github.com/lucasb-eyer/plattli/blob/main/CHANGELOG.md
Project-URL: Homepage, https://github.com/lucasb-eyer/plattli
Project-URL: Issues, https://github.com/lucasb-eyer/plattli/issues
Project-URL: Repository, https://github.com/lucasb-eyer/plattli
